{"address":"44 CROSBY ST","count":4,"properties":[{"a":"44 CROSBY ST","s":"PENDLE HILL","p":"2145","t":"Residence","$":325000,"d":"2001-12-21","l":"221","m":0,"y":2002,"z":"","n":"R"},{"a":"44 CROSBY ST","s":"PENDLE HILL","p":"2145","t":"Residence","$":248000,"d":"2001-12-07","l":"221","m":0,"y":2002,"z":"","n":"R"},{"a":"44 CROSBY ST","s":"PENDLE HILL","p":"2145","t":"Residence","$":258000,"d":"2001-12-10","l":"221","m":0,"y":2002,"z":"","n":"R"},{"a":"44 CROSBY ST","s":"PENDLE HILL","p":"2145","t":"Residence","$":330000,"d":"2002-06-03","l":"221","m":0,"y":2002,"z":"","n":"R"}]}