{"address":"601/349 NEW SOUTH HEAD RD","count":4,"properties":[{"a":"601/349 NEW SOUTH HEAD RD","s":"DOUBLE BAY","p":"2028","t":"Residence","$":860000,"d":"2008-01-08","l":"210","m":0,"y":2008,"z":"","n":"R"},{"a":"601/349 NEW SOUTH HEAD RD","s":"DOUBLE BAY","p":"2028","t":"Residence","$":860000,"d":"2008-01-08","l":"210","m":0,"y":2008,"z":"","n":"R"},{"a":"601/349 NEW SOUTH HEAD RD","s":"DOUBLE BAY","p":"2028","t":"Residence","$":860000,"d":"2008-01-08","l":"210","m":0,"y":2008,"z":"","n":"R"},{"a":"601/349 NEW SOUTH HEAD RD","s":"DOUBLE BAY","p":"2028","t":"Residence","$":860000,"d":"2008-01-08","l":"210","m":0,"y":2008,"z":"","n":"R"}]}