{"address":"OLD BUNDARRA RD","count":5,"properties":[{"a":"OLD BUNDARRA RD","s":"INVERELL","p":"2360","t":"Vacant Land","$":110000,"d":"2011-07-27","l":"188","m":1,"y":2011,"z":"R","n":"V"},{"a":"OLD BUNDARRA RD","s":"INVERELL","p":"2360","t":"Vacant Land","$":105000,"d":"2010-12-17","l":"188","m":1.077,"y":2011,"z":"","n":"V"},{"a":"OLD BUNDARRA RD","s":"IRONBARK","p":"2347","t":"FARM","$":280000,"d":"2011-07-08","l":"666","m":380.6,"y":2011,"z":"RU1","n":"3"},{"a":"OLD BUNDARRA RD","s":"BARRABA","p":"2347","t":"FARM","$":480000,"d":"2011-07-12","l":"666","m":729.1,"y":2011,"z":"RU1","n":"3"},{"a":"OLD BUNDARRA RD","s":"IRONBARK","p":"2347","t":"FARM","$":675000,"d":"2011-07-12","l":"666","m":824.041,"y":2011,"z":"RU1","n":"3"}]}