{"address":"4/32 BUNDARA CRES","count":6,"properties":[{"a":"4/32 BUNDARA CRES","s":"TUMUT","p":"2720","t":"Residence","$":562500,"d":"2006-06-27","l":"072","m":0,"y":2006,"z":"","n":"R"},{"a":"4/32 BUNDARA CRES","s":"TUMUT","p":"2720","t":"Residence","$":562500,"d":"2006-06-27","l":"072","m":0,"y":2006,"z":"","n":"R"},{"a":"4/32 BUNDARA CRES","s":"TUMUT","p":"2720","t":"Residence","$":562500,"d":"2006-06-27","l":"072","m":0,"y":2006,"z":"","n":"R"},{"a":"4/32 BUNDARA CRES","s":"TUMUT","p":"2720","t":"Residence","$":562500,"d":"2006-06-27","l":"072","m":0,"y":2006,"z":"","n":"R"},{"a":"4/32 BUNDARA CRES","s":"TUMUT","p":"2720","t":"Residence","$":562500,"d":"2006-06-27","l":"072","m":0,"y":2006,"z":"","n":"R"},{"a":"4/32 BUNDARA CRES","s":"TUMUT","p":"2720","t":"Residence","$":562500,"d":"2006-06-27","l":"072","m":0,"y":2006,"z":"","n":"R"}]}