{"address":"CRANESBILL WAY","count":9,"properties":[{"a":"CRANESBILL WAY","s":"FIGTREE","p":"2525","t":"Vacant Land","$":355000,"d":"2013-05-28","l":"103","m":629.3,"y":2013,"z":"R2","n":"V"},{"a":"CRANESBILL WAY","s":"FIGTREE","p":"2525","t":"Vacant Land","$":375000,"d":"2013-05-24","l":"103","m":750.3,"y":2013,"z":"","n":"V"},{"a":"CRANESBILL WAY","s":"FIGTREE","p":"2525","t":"Vacant Land","$":385000,"d":"2013-05-23","l":"103","m":705.8,"y":2013,"z":"","n":"V"},{"a":"CRANESBILL WAY","s":"FIGTREE","p":"2525","t":"Vacant Land","$":400000,"d":"2013-05-24","l":"103","m":827.9,"y":2013,"z":"","n":"V"},{"a":"CRANESBILL WAY","s":"FIGTREE","p":"2525","t":"Vacant Land","$":415000,"d":"2013-05-24","l":"103","m":783.4,"y":2013,"z":"R2","n":"V"},{"a":"CRANESBILL WAY","s":"FIGTREE","p":"2525","t":"Vacant Land","$":330000,"d":"2013-10-28","l":"103","m":632.7,"y":2013,"z":"R2","n":"V"},{"a":"CRANESBILL WAY","s":"FIGTREE","p":"2525","t":"Vacant Land","$":377500,"d":"2013-09-26","l":"103","m":707.4,"y":2013,"z":"R2","n":"V"},{"a":"CRANESBILL WAY","s":"FIGTREE","p":"2525","t":"Vacant Land","$":375000,"d":"2013-08-30","l":"103","m":708.3,"y":2013,"z":"R2","n":"V"},{"a":"CRANESBILL WAY","s":"FIGTREE","p":"2525","t":"Vacant Land","$":375000,"d":"2013-08-30","l":"103","m":744.3,"y":2013,"z":"R2","n":"V"}]}