{"address":"13 STATION ST","count":4,"properties":[{"a":"13 STATION ST","s":"BONNELLS BAY","p":"2264","t":"Residence","$":1000000,"d":"2021-05-14","l":"004","m":607,"y":2021,"z":"R2","n":"R"},{"a":"13 STATION ST","s":"WOY WOY","p":"2256","t":"Residence","$":870000,"d":"2021-08-10","l":"259","m":461.6,"y":2021,"z":"R1","n":"R"},{"a":"13 STATION ST","s":"BANGALOW","p":"2479","t":"COMMERCIAL","$":3135000,"d":"2021-10-25","l":"150","m":611.1,"y":2021,"z":"B2","n":"3"},{"a":"13 STATION ST","s":"MENANGLE","p":"2568","t":"Vacant Land","$":758900,"d":"2021-11-26","l":"226","m":1292,"y":2021,"z":"R2","n":"V"}]}