{"address":"TYSONS RD","count":5,"properties":[{"a":"TYSONS RD","s":"TABBITA","p":"2652","t":"RURAL","$":2260,"d":"2017-05-17","l":"052","m":3801,"y":2017,"z":"","n":"3"},{"a":"TYSONS RD","s":"TABBITA","p":"2652","t":"RURAL","$":2260,"d":"2017-05-17","l":"052","m":7.669,"y":2017,"z":"RU1","n":"3"},{"a":"TYSONS RD","s":"TABBITA","p":"2652","t":"RURAL","$":2260,"d":"2017-05-17","l":"052","m":7.669,"y":2017,"z":"RU1","n":"3"},{"a":"TYSONS RD","s":"TABBITA","p":"2652","t":"RURAL","$":2260,"d":"2017-05-17","l":"052","m":3801,"y":2017,"z":"","n":"3"},{"a":"TYSONS RD","s":"TABBITA","p":"2652","t":"RURAL","$":2260,"d":"2017-05-17","l":"052","m":7.669,"y":2017,"z":"RU1","n":"3"}]}