{"address":"326 ARDEN ST","count":4,"properties":[{"a":"326 ARDEN ST","s":"COOGEE","p":"2034","t":"Unit","$":21775000,"d":"2016-12-08","l":"207","m":1362.13,"y":2017,"z":"R3","n":"3"},{"a":"326 ARDEN ST","s":"COOGEE","p":"2034","t":"Residence","$":780000,"d":"2017-05-05","l":"207","m":66,"y":2017,"z":"","n":"R"},{"a":"326 ARDEN ST","s":"COOGEE","p":"2034","t":"Residence","$":1290000,"d":"2017-05-10","l":"207","m":103,"y":2017,"z":"","n":"R"},{"a":"326 ARDEN ST","s":"COOGEE","p":"2034","t":"Unit","$":1340000,"d":"2017-05-02","l":"207","m":102,"y":2017,"z":"","n":"3"}]}