{"address":"912/1 B PEARL ST","count":12,"properties":[{"a":"912/1 B PEARL ST","s":"HURSTVILLE","p":"2220","t":"Residence","$":525000,"d":"2016-06-20","l":"140","m":84,"y":2017,"z":"","n":"R"},{"a":"912/1 B PEARL ST","s":"HURSTVILLE","p":"2220","t":"Residence","$":618000,"d":"2017-08-18","l":"140","m":84,"y":2017,"z":"","n":"R"},{"a":"912/1 B PEARL ST","s":"HURSTVILLE","p":"2220","t":"Residence","$":525000,"d":"2016-06-20","l":"140","m":84,"y":2017,"z":"","n":"R"},{"a":"912/1 B PEARL ST","s":"HURSTVILLE","p":"2220","t":"Residence","$":618000,"d":"2017-08-18","l":"140","m":84,"y":2017,"z":"","n":"R"},{"a":"912/1 B PEARL ST","s":"HURSTVILLE","p":"2220","t":"Residence","$":525000,"d":"2016-06-20","l":"140","m":84,"y":2017,"z":"","n":"R"},{"a":"912/1 B PEARL ST","s":"HURSTVILLE","p":"2220","t":"Residence","$":618000,"d":"2017-08-18","l":"140","m":84,"y":2017,"z":"","n":"R"},{"a":"912/1 B PEARL ST","s":"HURSTVILLE","p":"2220","t":"Residence","$":525000,"d":"2016-06-20","l":"140","m":84,"y":2017,"z":"","n":"R"},{"a":"912/1 B PEARL ST","s":"HURSTVILLE","p":"2220","t":"Residence","$":618000,"d":"2017-08-18","l":"140","m":84,"y":2017,"z":"","n":"R"},{"a":"912/1 B PEARL ST","s":"HURSTVILLE","p":"2220","t":"Residence","$":525000,"d":"2016-06-20","l":"140","m":84,"y":2017,"z":"","n":"R"},{"a":"912/1 B PEARL ST","s":"HURSTVILLE","p":"2220","t":"Residence","$":618000,"d":"2017-08-18","l":"140","m":84,"y":2017,"z":"","n":"R"},{"a":"912/1 B PEARL ST","s":"HURSTVILLE","p":"2220","t":"Residence","$":525000,"d":"2016-06-20","l":"140","m":84,"y":2017,"z":"","n":"R"},{"a":"912/1 B PEARL ST","s":"HURSTVILLE","p":"2220","t":"Residence","$":618000,"d":"2017-08-18","l":"140","m":84,"y":2017,"z":"","n":"R"}]}