{"address":"14 STANLEY ST","count":4,"properties":[{"a":"14 STANLEY ST","s":"BELMONT","p":"2280","t":"Residence","$":240000,"d":"2003-08-15","l":"004","m":645,"y":2003,"z":"A","n":"R"},{"a":"14 STANLEY ST","s":"LEICHHARDT","p":"2040","t":"Residence","$":572000,"d":"2002-12-16","l":"205","m":0,"y":2003,"z":"A","n":"R"},{"a":"14 STANLEY ST","s":"HILL TOP","p":"2575","t":"Residence","$":268000,"d":"2003-02-24","l":"102","m":1119,"y":2003,"z":"Z","n":"R"},{"a":"14 STANLEY ST","s":"FORSTER","p":"2428","t":"Residence","$":250000,"d":"2003-09-15","l":"013","m":467.9,"y":2003,"z":"A","n":"R"}]}