{"address":"616/5 GLADSTONE ST","count":52,"properties":[{"a":"616/5 GLADSTONE ST","s":"MERRYLANDS","p":"2160","t":"Residence","$":794962,"d":"2024-04-23","l":"261","m":105,"y":2024,"z":"","n":"R"},{"a":"616/5 GLADSTONE ST","s":"MERRYLANDS","p":"2160","t":"Residence","$":794962,"d":"2024-04-23","l":"261","m":105,"y":2024,"z":"","n":"R"},{"a":"616/5 GLADSTONE ST","s":"MERRYLANDS","p":"2160","t":"Residence","$":794962,"d":"2024-04-23","l":"261","m":105,"y":2024,"z":"","n":"R"},{"a":"616/5 GLADSTONE ST","s":"MERRYLANDS","p":"2160","t":"Residence","$":794962,"d":"2024-04-23","l":"261","m":105,"y":2024,"z":"","n":"R"},{"a":"616/5 GLADSTONE ST","s":"MERRYLANDS","p":"2160","t":"Residence","$":794962,"d":"2024-04-23","l":"261","m":105,"y":2024,"z":"","n":"R"},{"a":"616/5 GLADSTONE ST","s":"MERRYLANDS","p":"2160","t":"Residence","$":794962,"d":"2024-04-23","l":"261","m":105,"y":2024,"z":"","n":"R"},{"a":"616/5 GLADSTONE ST","s":"MERRYLANDS","p":"2160","t":"Residence","$":794962,"d":"2024-04-23","l":"261","m":105,"y":2024,"z":"","n":"R"},{"a":"616/5 GLADSTONE ST","s":"MERRYLANDS","p":"2160","t":"Residence","$":794962,"d":"2024-04-23","l":"261","m":105,"y":2024,"z":"","n":"R"},{"a":"616/5 GLADSTONE ST","s":"MERRYLANDS","p":"2160","t":"Residence","$":794962,"d":"2024-04-23","l":"261","m":105,"y":2024,"z":"","n":"R"},{"a":"616/5 GLADSTONE ST","s":"MERRYLANDS","p":"2160","t":"Residence","$":794962,"d":"2024-04-23","l":"261","m":105,"y":2024,"z":"","n":"R"},{"a":"616/5 GLADSTONE ST","s":"MERRYLANDS","p":"2160","t":"Residence","$":794962,"d":"2024-04-23","l":"261","m":105,"y":2024,"z":"","n":"R"},{"a":"616/5 GLADSTONE ST","s":"MERRYLANDS","p":"2160","t":"Residence","$":794962,"d":"2024-04-23","l":"261","m":105,"y":2024,"z":"","n":"R"},{"a":"616/5 GLADSTONE ST","s":"MERRYLANDS","p":"2160","t":"Residence","$":794962,"d":"2024-04-23","l":"261","m":105,"y":2024,"z":"","n":"R"},{"a":"616/5 GLADSTONE ST","s":"MERRYLANDS","p":"2160","t":"Residence","$":794962,"d":"2024-04-23","l":"261","m":105,"y":2024,"z":"","n":"R"},{"a":"616/5 GLADSTONE ST","s":"MERRYLANDS","p":"2160","t":"Residence","$":794962,"d":"2024-04-23","l":"261","m":105,"y":2024,"z":"","n":"R"},{"a":"616/5 GLADSTONE ST","s":"MERRYLANDS","p":"2160","t":"Residence","$":794962,"d":"2024-04-23","l":"261","m":105,"y":2024,"z":"","n":"R"},{"a":"616/5 GLADSTONE ST","s":"MERRYLANDS","p":"2160","t":"Residence","$":794962,"d":"2024-04-23","l":"261","m":105,"y":2024,"z":"","n":"R"},{"a":"616/5 GLADSTONE ST","s":"MERRYLANDS","p":"2160","t":"Residence","$":794962,"d":"2024-04-23","l":"261","m":105,"y":2024,"z":"","n":"R"},{"a":"616/5 GLADSTONE ST","s":"MERRYLANDS","p":"2160","t":"Residence","$":794962,"d":"2024-04-23","l":"261","m":105,"y":2024,"z":"","n":"R"},{"a":"616/5 GLADSTONE ST","s":"MERRYLANDS","p":"2160","t":"Residence","$":794962,"d":"2024-04-23","l":"261","m":105,"y":2024,"z":"","n":"R"},{"a":"616/5 GLADSTONE ST","s":"MERRYLANDS","p":"2160","t":"Residence","$":794963,"d":"2024-09-13","l":"261","m":105,"y":2024,"z":"","n":"R"},{"a":"616/5 GLADSTONE ST","s":"MERRYLANDS","p":"2160","t":"Residence","$":794962,"d":"2024-04-23","l":"261","m":105,"y":2024,"z":"","n":"R"},{"a":"616/5 GLADSTONE ST","s":"MERRYLANDS","p":"2160","t":"Residence","$":794963,"d":"2024-09-13","l":"261","m":105,"y":2024,"z":"","n":"R"},{"a":"616/5 GLADSTONE ST","s":"MERRYLANDS","p":"2160","t":"Residence","$":794962,"d":"2024-04-23","l":"261","m":105,"y":2024,"z":"","n":"R"},{"a":"616/5 GLADSTONE ST","s":"MERRYLANDS","p":"2160","t":"Residence","$":794963,"d":"2024-09-13","l":"261","m":105,"y":2024,"z":"","n":"R"},{"a":"616/5 GLADSTONE ST","s":"MERRYLANDS","p":"2160","t":"Residence","$":794962,"d":"2024-04-23","l":"261","m":105,"y":2024,"z":"","n":"R"},{"a":"616/5 GLADSTONE ST","s":"MERRYLANDS","p":"2160","t":"Residence","$":794963,"d":"2024-09-13","l":"261","m":105,"y":2024,"z":"","n":"R"},{"a":"616/5 GLADSTONE ST","s":"MERRYLANDS","p":"2160","t":"Residence","$":794962,"d":"2024-04-23","l":"261","m":105,"y":2024,"z":"","n":"R"},{"a":"616/5 GLADSTONE ST","s":"MERRYLANDS","p":"2160","t":"Residence","$":794963,"d":"2024-09-13","l":"261","m":105,"y":2024,"z":"","n":"R"},{"a":"616/5 GLADSTONE ST","s":"MERRYLANDS","p":"2160","t":"Residence","$":794962,"d":"2024-04-23","l":"261","m":105,"y":2024,"z":"","n":"R"},{"a":"616/5 GLADSTONE ST","s":"MERRYLANDS","p":"2160","t":"Residence","$":794963,"d":"2024-09-13","l":"261","m":105,"y":2024,"z":"","n":"R"},{"a":"616/5 GLADSTONE ST","s":"MERRYLANDS","p":"2160","t":"Residence","$":794962,"d":"2024-04-23","l":"261","m":105,"y":2024,"z":"","n":"R"},{"a":"616/5 GLADSTONE ST","s":"MERRYLANDS","p":"2160","t":"Residence","$":794963,"d":"2024-09-13","l":"261","m":105,"y":2024,"z":"","n":"R"},{"a":"616/5 GLADSTONE ST","s":"MERRYLANDS","p":"2160","t":"Residence","$":794962,"d":"2024-04-23","l":"261","m":105,"y":2024,"z":"","n":"R"},{"a":"616/5 GLADSTONE ST","s":"MERRYLANDS","p":"2160","t":"Residence","$":794963,"d":"2024-09-13","l":"261","m":105,"y":2024,"z":"","n":"R"},{"a":"616/5 GLADSTONE ST","s":"MERRYLANDS","p":"2160","t":"Residence","$":794962,"d":"2024-04-23","l":"261","m":105,"y":2024,"z":"","n":"R"},{"a":"616/5 GLADSTONE ST","s":"MERRYLANDS","p":"2160","t":"Residence","$":794963,"d":"2024-09-13","l":"261","m":105,"y":2024,"z":"","n":"R"},{"a":"616/5 GLADSTONE ST","s":"MERRYLANDS","p":"2160","t":"Residence","$":794962,"d":"2024-04-23","l":"261","m":105,"y":2024,"z":"","n":"R"},{"a":"616/5 GLADSTONE ST","s":"MERRYLANDS","p":"2160","t":"Residence","$":794963,"d":"2024-09-13","l":"261","m":105,"y":2024,"z":"","n":"R"},{"a":"616/5 GLADSTONE ST","s":"MERRYLANDS","p":"2160","t":"Residence","$":794962,"d":"2024-04-23","l":"261","m":105,"y":2024,"z":"","n":"R"},{"a":"616/5 GLADSTONE ST","s":"MERRYLANDS","p":"2160","t":"Residence","$":794963,"d":"2024-09-13","l":"261","m":105,"y":2024,"z":"","n":"R"},{"a":"616/5 GLADSTONE ST","s":"MERRYLANDS","p":"2160","t":"Residence","$":794962,"d":"2024-04-23","l":"261","m":105,"y":2024,"z":"","n":"R"},{"a":"616/5 GLADSTONE ST","s":"MERRYLANDS","p":"2160","t":"Residence","$":794963,"d":"2024-09-13","l":"261","m":105,"y":2024,"z":"","n":"R"},{"a":"616/5 GLADSTONE ST","s":"MERRYLANDS","p":"2160","t":"Residence","$":794962,"d":"2024-04-23","l":"261","m":105,"y":2024,"z":"","n":"R"},{"a":"616/5 GLADSTONE ST","s":"MERRYLANDS","p":"2160","t":"Residence","$":794963,"d":"2024-09-13","l":"261","m":105,"y":2024,"z":"","n":"R"},{"a":"616/5 GLADSTONE ST","s":"MERRYLANDS","p":"2160","t":"Residence","$":794962,"d":"2024-04-23","l":"261","m":105,"y":2024,"z":"","n":"R"},{"a":"616/5 GLADSTONE ST","s":"MERRYLANDS","p":"2160","t":"Residence","$":794963,"d":"2024-09-13","l":"261","m":105,"y":2024,"z":"","n":"R"},{"a":"616/5 GLADSTONE ST","s":"MERRYLANDS","p":"2160","t":"Residence","$":794962,"d":"2024-04-23","l":"261","m":105,"y":2024,"z":"","n":"R"},{"a":"616/5 GLADSTONE ST","s":"MERRYLANDS","p":"2160","t":"Residence","$":794963,"d":"2024-09-13","l":"261","m":105,"y":2024,"z":"","n":"R"},{"a":"616/5 GLADSTONE ST","s":"MERRYLANDS","p":"2160","t":"Residence","$":794962,"d":"2024-04-23","l":"261","m":105,"y":2024,"z":"","n":"R"},{"a":"616/5 GLADSTONE ST","s":"MERRYLANDS","p":"2160","t":"Residence","$":794963,"d":"2024-09-13","l":"261","m":105,"y":2024,"z":"","n":"R"},{"a":"616/5 GLADSTONE ST","s":"MERRYLANDS","p":"2160","t":"Residence","$":794962,"d":"2024-04-23","l":"261","m":105,"y":2024,"z":"","n":"R"}]}