{"address":"GLENNIE ST","count":6,"properties":[{"a":"GLENNIE ST","s":"CAMBERWELL","p":"2330","t":"Residence","$":115000,"d":"2003-02-18","l":"012","m":2023,"y":2003,"z":"R","n":"R"},{"a":"GLENNIE ST","s":"CAMBERWELL","p":"2330","t":"Residence","$":107000,"d":"2003-01-10","l":"012","m":2023,"y":2003,"z":"R","n":"R"},{"a":"GLENNIE ST","s":"CAMBERWELL","p":"2330","t":"Residence","$":130000,"d":"2003-01-15","l":"012","m":1.214,"y":2003,"z":"R","n":"R"},{"a":"GLENNIE ST","s":"CAMBERWELL","p":"2330","t":"Vacant Land","$":9000,"d":"2003-04-29","l":"012","m":644.9,"y":2003,"z":"R","n":"V"},{"a":"GLENNIE ST","s":"CAMBERWELL","p":"2330","t":"Residence","$":180000,"d":"2003-04-16","l":"012","m":2042,"y":2003,"z":"R","n":"R"},{"a":"GLENNIE ST","s":"CAMBERWELL","p":"2330","t":"Vacant Land","$":38000,"d":"2003-05-09","l":"012","m":5261,"y":2003,"z":"R","n":"V"}]}