{"address":"8 WILLIAM ST","count":5,"properties":[{"a":"8 WILLIAM ST","s":"TELARAH","p":"2320","t":"Residence","$":300000,"d":"2013-07-19","l":"005","m":347.8,"y":2013,"z":"R1","n":"R"},{"a":"8 WILLIAM ST","s":"MAYFIELD","p":"2304","t":"Residence","$":329000,"d":"2012-12-10","l":"008","m":490.4,"y":2013,"z":"R2","n":"R"},{"a":"8 WILLIAM ST","s":"MOONBI","p":"2353","t":"Residence","$":235000,"d":"2013-05-01","l":"666","m":2,"y":2013,"z":"RU4","n":"R"},{"a":"8 WILLIAM ST","s":"GOL GOL","p":"2738","t":"Residence","$":145000,"d":"2013-09-19","l":"255","m":1154,"y":2013,"z":"RU5","n":"R"},{"a":"8 WILLIAM ST","s":"BALMAIN EAST","p":"2041","t":"Residence","$":3180000,"d":"2013-08-29","l":"205","m":233.7,"y":2013,"z":"A","n":"R"}]}