{"address":"VALLETTA DR","count":10,"properties":[{"a":"VALLETTA DR","s":"MARAYLYA","p":"2765","t":"Vacant Land","$":345000,"d":"2020-05-25","l":"081","m":270,"y":2020,"z":"","n":"V"},{"a":"VALLETTA DR","s":"MARAYLYA","p":"2765","t":"Vacant Land","$":337000,"d":"2020-06-04","l":"081","m":270,"y":2020,"z":"R3","n":"V"},{"a":"VALLETTA DR","s":"MARAYLYA","p":"2765","t":"Vacant Land","$":344000,"d":"2020-06-11","l":"081","m":270,"y":2020,"z":"R3","n":"V"},{"a":"VALLETTA DR","s":"MARAYLYA","p":"2765","t":"Vacant Land","$":350000,"d":"2020-07-03","l":"081","m":270,"y":2020,"z":"R3","n":"V"},{"a":"VALLETTA DR","s":"MARAYLYA","p":"2765","t":"Vacant Land","$":345000,"d":"2020-08-28","l":"081","m":270,"y":2020,"z":"R3","n":"V"},{"a":"VALLETTA DR","s":"MARAYLYA","p":"2765","t":"Vacant Land","$":345000,"d":"2020-12-04","l":"081","m":270,"y":2020,"z":"R3","n":"V"},{"a":"VALLETTA DR","s":"MARAYLYA","p":"2765","t":"Vacant Land","$":345000,"d":"2020-12-04","l":"081","m":270,"y":2020,"z":"R3","n":"V"},{"a":"VALLETTA DR","s":"MARAYLYA","p":"2765","t":"Vacant Land","$":570000,"d":"2020-12-21","l":"081","m":550,"y":2020,"z":"R2","n":"V"},{"a":"VALLETTA DR","s":"MARAYLYA","p":"2765","t":"Vacant Land","$":599000,"d":"2020-12-24","l":"081","m":550,"y":2020,"z":"R2","n":"V"},{"a":"VALLETTA DR","s":"MARAYLYA","p":"2765","t":"Vacant Land","$":345000,"d":"2020-12-21","l":"081","m":270,"y":2020,"z":"R3","n":"V"}]}