{"address":"PH GRENFELL","count":5,"properties":[{"a":"PH GRENFELL","s":"QUIRINDI","p":"2343","t":"FARM","$":2750000,"d":"2004-07-01","l":"301","m":403.6,"y":2005,"z":"R","n":"3"},{"a":"PH GRENFELL","s":"QUIRINDI","p":"2343","t":"FARM","$":2750000,"d":"2004-07-01","l":"301","m":139.5,"y":2005,"z":"R","n":"3"},{"a":"PH GRENFELL","s":"QUIRINDI","p":"2343","t":"FARM","$":2750000,"d":"2004-07-01","l":"301","m":2.152,"y":2005,"z":"R","n":"3"},{"a":"PH GRENFELL","s":"QUIRINDI","p":"2343","t":"FARM","$":2750000,"d":"2004-07-01","l":"301","m":67.7,"y":2005,"z":"R","n":"3"},{"a":"PH GRENFELL","s":"QUIRINDI","p":"2343","t":"FARM","$":1200000,"d":"2005-03-07","l":"301","m":479.8,"y":2005,"z":"R","n":"3"}]}