{"address":"36 CHURCH ST","count":5,"properties":[{"a":"36 CHURCH ST","s":"RYDE","p":"2112","t":"Residence","$":660000,"d":"2012-12-18","l":"090","m":240.2,"y":2012,"z":"B4","n":"R"},{"a":"36 CHURCH ST","s":"SINGLETON","p":"2330","t":"Residence","$":423000,"d":"2011-12-22","l":"012","m":746.1,"y":2012,"z":"A","n":"R"},{"a":"36 CHURCH ST","s":"PARRAMATTA","p":"2150","t":"COMMERCIAL","$":1500000,"d":"2012-01-17","l":"089","m":938.9,"y":2012,"z":"B5","n":"3"},{"a":"36 CHURCH ST","s":"STOCKTON","p":"2295","t":"Residence","$":562500,"d":"2012-07-02","l":"008","m":347.8,"y":2012,"z":"R2","n":"R"},{"a":"36 CHURCH ST","s":"ALBION PARK","p":"2527","t":"Residence","$":335000,"d":"2011-12-21","l":"100","m":692.9,"y":2012,"z":"A","n":"R"}]}