{"address":"CHARLIE ST","count":11,"properties":[{"a":"CHARLIE ST","s":"MIDDLETON GRANGE","p":"2171","t":"Vacant Land","$":249000,"d":"2012-10-04","l":"223","m":375,"y":2012,"z":"R1","n":"V"},{"a":"CHARLIE ST","s":"MIDDLETON GRANGE","p":"2171","t":"Vacant Land","$":249900,"d":"2012-11-06","l":"223","m":375,"y":2012,"z":"R1","n":"V"},{"a":"CHARLIE ST","s":"MIDDLETON GRANGE","p":"2171","t":"Vacant Land","$":224900,"d":"2012-11-09","l":"223","m":300,"y":2012,"z":"R1","n":"V"},{"a":"CHARLIE ST","s":"MIDDLETON GRANGE","p":"2171","t":"Vacant Land","$":249900,"d":"2012-11-01","l":"223","m":375,"y":2012,"z":"R1","n":"V"},{"a":"CHARLIE ST","s":"MIDDLETON GRANGE","p":"2171","t":"Vacant Land","$":225900,"d":"2012-11-29","l":"223","m":433.7,"y":2012,"z":"R1","n":"V"},{"a":"CHARLIE ST","s":"MIDDLETON GRANGE","p":"2171","t":"Vacant Land","$":285900,"d":"2012-11-28","l":"223","m":575.8,"y":2012,"z":"R1","n":"V"},{"a":"CHARLIE ST","s":"MIDDLETON GRANGE","p":"2171","t":"Vacant Land","$":249900,"d":"2012-10-24","l":"223","m":375,"y":2012,"z":"R1","n":"V"},{"a":"CHARLIE ST","s":"MIDDLETON GRANGE","p":"2171","t":"Vacant Land","$":249900,"d":"2012-10-03","l":"223","m":375,"y":2012,"z":"R1","n":"V"},{"a":"CHARLIE ST","s":"MIDDLETON GRANGE","p":"2171","t":"Vacant Land","$":224900,"d":"2012-10-11","l":"223","m":300,"y":2012,"z":"R1","n":"V"},{"a":"CHARLIE ST","s":"MIDDLETON GRANGE","p":"2171","t":"Vacant Land","$":246900,"d":"2012-09-09","l":"223","m":455.4,"y":2012,"z":"R1","n":"V"},{"a":"CHARLIE ST","s":"MIDDLETON GRANGE","p":"2171","t":"Vacant Land","$":289900,"d":"2012-10-11","l":"223","m":504,"y":2012,"z":"R1","n":"V"}]}