{"address":"LACHLAN VALLEY WAY","count":21,"properties":[{"a":"LACHLAN VALLEY WAY","s":"JEMALONG","p":"2871","t":"FARM LAND","$":10000,"d":"2017-12-15","l":"117","m":2.006,"y":2018,"z":"RU1","n":"3"},{"a":"LACHLAN VALLEY WAY","s":"GODFREYS CREEK","p":"2586","t":"FARM","$":757500,"d":"2018-01-11","l":"021","m":303.039,"y":2018,"z":"","n":"3"},{"a":"LACHLAN VALLEY WAY","s":"GODFREYS CREEK","p":"2586","t":"Residence","$":920000,"d":"2018-01-11","l":"021","m":245.5,"y":2018,"z":"","n":"R"},{"a":"LACHLAN VALLEY WAY","s":"BOOROWA","p":"2586","t":"Vacant Land","$":3346,"d":"2017-12-22","l":"021","m":5.26,"y":2018,"z":"","n":"V"},{"a":"LACHLAN VALLEY WAY","s":"YASS","p":"2582","t":"FARM","$":8435477,"d":"2017-12-14","l":"528","m":254.8,"y":2018,"z":"RU1","n":"3"},{"a":"LACHLAN VALLEY WAY","s":"FAIRHOLME","p":"2871","t":"FARMLAND","$":694400,"d":"2018-01-25","l":"244","m":127,"y":2018,"z":"RU1","n":"3"},{"a":"LACHLAN VALLEY WAY","s":"FAIRHOLME","p":"2871","t":"FARMLAND","$":694400,"d":"2018-01-25","l":"244","m":68.7,"y":2018,"z":"RU1","n":"3"},{"a":"LACHLAN VALLEY WAY","s":"COWRA","p":"2794","t":"Vacant Land","$":585000,"d":"2018-01-31","l":"042","m":67.37,"y":2018,"z":"","n":"V"},{"a":"LACHLAN VALLEY WAY","s":"BOOROWA","p":"2586","t":"Residence","$":1000000,"d":"2018-04-03","l":"266","m":11.135,"y":2018,"z":"RU1","n":"R"},{"a":"LACHLAN VALLEY WAY","s":"WALLANTHERY","p":"2675","t":"Vacant Land","$":450000,"d":"2018-04-06","l":"052","m":8778,"y":2018,"z":"RU1","n":"V"},{"a":"LACHLAN VALLEY WAY","s":"FORBES","p":"2871","t":"Residence","$":350000,"d":"2018-04-13","l":"117","m":1.255,"y":2018,"z":"RU4","n":"R"},{"a":"LACHLAN VALLEY WAY","s":"BOWNING","p":"2582","t":"Vacant Land","$":109500,"d":"2017-12-01","l":"528","m":84.18,"y":2018,"z":"","n":"V"},{"a":"LACHLAN VALLEY WAY","s":"BOWNING","p":"2582","t":"Vacant Land","$":220500,"d":"2017-12-01","l":"528","m":84.18,"y":2018,"z":"","n":"V"},{"a":"LACHLAN VALLEY WAY","s":"COWRA","p":"2794","t":"Vacant Land","$":681880,"d":"2018-04-09","l":"042","m":63.4,"y":2018,"z":"","n":"V"},{"a":"LACHLAN VALLEY WAY","s":"LAKE CARGELLIGO","p":"2672","t":"Vacant Land","$":3770,"d":"2018-05-25","l":"244","m":20.38,"y":2018,"z":"","n":"V"},{"a":"LACHLAN VALLEY WAY","s":"HILLSTON","p":"2675","t":"FARM","$":175000,"d":"2018-06-21","l":"052","m":17.57,"y":2018,"z":"R5","n":"3"},{"a":"LACHLAN VALLEY WAY","s":"FORBES","p":"2871","t":"FARM","$":664605,"d":"2018-07-17","l":"117","m":179.3,"y":2018,"z":"RU1","n":"3"},{"a":"LACHLAN VALLEY WAY","s":"BOWNING","p":"2582","t":"Vacant Land","$":220500,"d":"2017-12-01","l":"528","m":25.5,"y":2018,"z":"","n":"V"},{"a":"LACHLAN VALLEY WAY","s":"LAKE CARGELLIGO","p":"2672","t":"Vacant Land","$":17066,"d":"2018-08-24","l":"244","m":148.6,"y":2018,"z":"","n":"V"},{"a":"LACHLAN VALLEY WAY","s":"GODFREYS CREEK","p":"2586","t":"FARM","$":2200000,"d":"2018-10-19","l":"266","m":369.186,"y":2018,"z":"RU1","n":"3"},{"a":"LACHLAN VALLEY WAY","s":"HILLSTON","p":"2675","t":"RURAL LAND","$":1000000,"d":"2018-12-03","l":"052","m":77.62,"y":2018,"z":"RU1","n":"3"}]}