{"address":"4 FRENCH AVE","count":5,"properties":[{"a":"4 FRENCH AVE","s":"BANKSTOWN","p":"2200","t":"Residence","$":492600,"d":"2022-04-29","l":"258","m":105,"y":2022,"z":"","n":"R"},{"a":"4 FRENCH AVE","s":"BANKSTOWN","p":"2200","t":"Residence","$":560000,"d":"2022-05-16","l":"258","m":132,"y":2022,"z":"","n":"R"},{"a":"4 FRENCH AVE","s":"BANKSTOWN","p":"2200","t":"Residence","$":505000,"d":"2022-06-07","l":"258","m":89,"y":2022,"z":"","n":"R"},{"a":"4 FRENCH AVE","s":"BANKSTOWN","p":"2200","t":"Residence","$":550000,"d":"2022-07-05","l":"258","m":118,"y":2022,"z":"","n":"R"},{"a":"4 FRENCH AVE","s":"BANKSTOWN","p":"2200","t":"Residence","$":515000,"d":"2022-08-17","l":"258","m":105,"y":2022,"z":"","n":"R"}]}