{"address":"16 CAMPBELL ST","count":4,"properties":[{"a":"16 CAMPBELL ST","s":"WINGHAM","p":"2429","t":"Residence","$":330000,"d":"2021-01-29","l":"268","m":1.583,"y":2021,"z":"R1","n":"R"},{"a":"16 CAMPBELL ST","s":"RENWICK","p":"2575","t":"Vacant Land","$":390000,"d":"2021-05-07","l":"102","m":851.7,"y":2021,"z":"R2","n":"V"},{"a":"16 CAMPBELL ST","s":"COOLAH","p":"2843","t":"Residence","$":187500,"d":"2021-05-28","l":"537","m":2010,"y":2021,"z":"R1","n":"R"},{"a":"16 CAMPBELL ST","s":"RAMSGATE","p":"2217","t":"Residence","$":2280000,"d":"2021-08-06","l":"276","m":459.94,"y":2021,"z":"R2","n":"R"}]}