{"address":"ROSELLA RD","count":4,"properties":[{"a":"ROSELLA RD","s":"GULMARRAD","p":"2463","t":"Vacant Land","$":130000,"d":"2005-08-04","l":"303","m":4000,"y":2005,"z":"R","n":"V"},{"a":"ROSELLA RD","s":"GULMARRAD","p":"2463","t":"SHED/LAND","$":145000,"d":"2004-10-07","l":"303","m":4314,"y":2005,"z":"R","n":"3"},{"a":"ROSELLA RD","s":"GULMARRAD","p":"2463","t":"Vacant Land","$":175000,"d":"2005-05-09","l":"303","m":8977,"y":2005,"z":"R","n":"V"},{"a":"ROSELLA RD","s":"GULMARRAD","p":"2463","t":"Vacant Land","$":350000,"d":"2005-11-04","l":"303","m":4314,"y":2005,"z":"R","n":"V"}]}