{"address":"6 RAILWAY ST","count":5,"properties":[{"a":"6 RAILWAY ST","s":"GALONG","p":"2585","t":"Residence","$":115000,"d":"2005-03-10","l":"037","m":3105,"y":2005,"z":"Z","n":"R"},{"a":"6 RAILWAY ST","s":"SOUTH KEMPSEY","p":"2440","t":"Residence","$":105000,"d":"2005-07-25","l":"157","m":1695,"y":2005,"z":"A","n":"R"},{"a":"6 RAILWAY ST","s":"COWRA","p":"2794","t":"Residence","$":165000,"d":"2005-12-07","l":"042","m":1011.83,"y":2005,"z":"B","n":"R"},{"a":"6 RAILWAY ST","s":"TENTERFIELD","p":"2372","t":"Residence","$":110000,"d":"2004-11-05","l":"250","m":910.6,"y":2005,"z":"Z","n":"R"},{"a":"6 RAILWAY ST","s":"HURLSTONE PARK","p":"2193","t":"Residence","$":400000,"d":"2005-05-06","l":"138","m":278.74,"y":2005,"z":"A","n":"R"}]}