{"address":"6 PARTRIDGE PL","count":6,"properties":[{"a":"6 PARTRIDGE PL","s":"SINGLETON HEIGHTS","p":"2330","t":"Vacant Land","$":105000,"d":"2004-07-02","l":"012","m":841,"y":2004,"z":"","n":"V"},{"a":"6 PARTRIDGE PL","s":"SINGLETON HEIGHTS","p":"2330","t":"Vacant Land","$":137000,"d":"2004-12-08","l":"012","m":841,"y":2004,"z":"","n":"V"},{"a":"6 PARTRIDGE PL","s":"SINGLETON HEIGHTS","p":"2330","t":"Vacant Land","$":105000,"d":"2004-07-02","l":"012","m":841,"y":2004,"z":"","n":"V"},{"a":"6 PARTRIDGE PL","s":"SINGLETON HEIGHTS","p":"2330","t":"Vacant Land","$":105000,"d":"2004-07-02","l":"012","m":841,"y":2004,"z":"","n":"V"},{"a":"6 PARTRIDGE PL","s":"SINGLETON HEIGHTS","p":"2330","t":"Vacant Land","$":105000,"d":"2004-07-02","l":"012","m":841,"y":2004,"z":"","n":"V"},{"a":"6 PARTRIDGE PL","s":"SINGLETON HEIGHTS","p":"2330","t":"Vacant Land","$":105000,"d":"2004-07-02","l":"012","m":841,"y":2004,"z":"","n":"V"}]}