{"address":"DANJERA DR","count":6,"properties":[{"a":"DANJERA DR","s":"ALBION PARK","p":"2527","t":"Residence","$":210000,"d":"2004-03-19","l":"100","m":600,"y":2004,"z":"A","n":"R"},{"a":"DANJERA DR","s":"ALBION PARK","p":"2527","t":"Vacant Land","$":239000,"d":"2004-07-30","l":"100","m":823.5,"y":2004,"z":"A","n":"V"},{"a":"DANJERA DR","s":"ALBION PARK","p":"2527","t":"Vacant Land","$":185000,"d":"2003-04-11","l":"100","m":765.6,"y":2004,"z":"A","n":"V"},{"a":"DANJERA DR","s":"ALBION PARK","p":"2527","t":"Property","$":225000,"d":"2003-12-14","l":"100","m":823.5,"y":2004,"z":"A","n":"3"},{"a":"DANJERA DR","s":"ALBION PARK","p":"2527","t":"Property","$":225000,"d":"2003-12-14","l":"100","m":823.5,"y":2004,"z":"A","n":"3"},{"a":"DANJERA DR","s":"ALBION PARK","p":"2527","t":"Vacant Land","$":133333,"d":"2004-08-30","l":"100","m":600,"y":2004,"z":"A","n":"V"}]}