{"address":"801/276 PITT ST","count":4,"properties":[{"a":"801/276 PITT ST","s":"SYDNEY","p":"2000","t":"COMMERCIAL","$":467500,"d":"2004-03-02","l":"708","m":0,"y":2004,"z":"","n":"3"},{"a":"801/276 PITT ST","s":"SYDNEY","p":"2000","t":"COMMERCIAL","$":467500,"d":"2004-03-02","l":"708","m":0,"y":2004,"z":"","n":"3"},{"a":"801/276 PITT ST","s":"SYDNEY","p":"2000","t":"COMMERCIAL","$":467500,"d":"2004-03-02","l":"208","m":0,"y":2004,"z":"","n":"3"},{"a":"801/276 PITT ST","s":"SYDNEY","p":"2000","t":"COMMERCIAL","$":467500,"d":"2004-03-02","l":"208","m":0,"y":2004,"z":"","n":"3"}]}