{"address":"HUME HWY","count":12,"properties":[{"a":"HUME HWY","s":"TARCUTTA","p":"2652","t":"FARM","$":4900000,"d":"2022-11-10","l":"575","m":420.355,"y":2023,"z":"","n":"3"},{"a":"HUME HWY","s":"MOUNT ADRAH","p":"2729","t":"Vacant Land","$":1163,"d":"2023-02-03","l":"265","m":2582,"y":2023,"z":"","n":"V"},{"a":"HUME HWY","s":"MOUNT ADRAH","p":"2729","t":"Vacant Land","$":1163,"d":"2023-02-03","l":"265","m":8054,"y":2023,"z":"","n":"V"},{"a":"HUME HWY","s":"MOUNT ADRAH","p":"2729","t":"Vacant Land","$":1163,"d":"2023-02-03","l":"265","m":2593,"y":2023,"z":"","n":"V"},{"a":"HUME HWY","s":"CULLERIN","p":"2581","t":"SUBSTATION","$":18716,"d":"2023-01-13","l":"526","m":0,"y":2023,"z":"","n":"3"},{"a":"HUME HWY","s":"CULLERIN","p":"2581","t":"Residence","$":1620000,"d":"2023-05-22","l":"526","m":139.3,"y":2023,"z":"","n":"R"},{"a":"HUME HWY","s":"CULLERIN","p":"2581","t":"Residence","$":2725000,"d":"2023-06-02","l":"526","m":409.89,"y":2023,"z":"","n":"R"},{"a":"HUME HWY","s":"CULLERIN","p":"2581","t":"FARM","$":2580000,"d":"2023-06-02","l":"526","m":409.89,"y":2023,"z":"","n":"3"},{"a":"HUME HWY","s":"SUTTON FOREST","p":"2577","t":"Vacant Land","$":3250000,"d":"2023-07-14","l":"102","m":36.92,"y":2023,"z":"","n":"V"},{"a":"HUME HWY","s":"CULLERIN","p":"2581","t":"FARM","$":2150000,"d":"2023-02-28","l":"526","m":221.693,"y":2023,"z":"","n":"3"},{"a":"HUME HWY","s":"CULLERIN","p":"2581","t":"FARM","$":1750000,"d":"2023-07-10","l":"526","m":153.62,"y":2023,"z":"","n":"3"},{"a":"HUME HWY","s":"CULLERIN","p":"2581","t":"FARM","$":1750000,"d":"2023-07-10","l":"526","m":153.62,"y":2023,"z":"","n":"3"}]}