{"address":"BUNDY RD","count":4,"properties":[{"a":"BUNDY RD","s":"BOURKE","p":"2840","t":"RURAL","$":1442569,"d":"2014-09-18","l":"239","m":19537,"y":2015,"z":"RU1","n":"3"},{"a":"BUNDY RD","s":"BOURKE","p":"2840","t":"FARM","$":3218000,"d":"2014-09-09","l":"239","m":12016,"y":2015,"z":"RU1","n":"3"},{"a":"BUNDY RD","s":"BOURKE","p":"2840","t":"FARM","$":3218000,"d":"2014-09-09","l":"239","m":11838,"y":2015,"z":"RU1","n":"3"},{"a":"BUNDY RD","s":"BOURKE","p":"2840","t":"FARM","$":3218000,"d":"2014-09-09","l":"239","m":420,"y":2015,"z":"RU1","n":"3"}]}