{"address":"BRUXNER HWY","count":4,"properties":[{"a":"BRUXNER HWY","s":"TABULAM","p":"2469","t":"FARM","$":98000,"d":"2014-12-12","l":"158","m":36.11,"y":2015,"z":"RU1","n":"3"},{"a":"BRUXNER HWY","s":"DRAKE","p":"2469","t":"Vacant Land","$":42000,"d":"2015-03-23","l":"250","m":17.56,"y":2015,"z":"RU1","n":"V"},{"a":"BRUXNER HWY","s":"WOODVIEW","p":"2470","t":"Residence","$":920000,"d":"2015-06-05","l":"151","m":142.1,"y":2015,"z":"RU1","n":"R"},{"a":"BRUXNER HWY","s":"MALLANGANEE","p":"2469","t":"FARM LAND","$":550000,"d":"2015-11-06","l":"158","m":102,"y":2015,"z":"RU1","n":"3"}]}