{"address":"12 VIOLET ST","count":5,"properties":[{"a":"12 VIOLET ST","s":"BRONTE","p":"2024","t":"Residence","$":1225000,"d":"2007-05-23","l":"209","m":309.8,"y":2007,"z":"A","n":"R"},{"a":"12 VIOLET ST","s":"CHATSWOOD","p":"2067","t":"Residence","$":890000,"d":"2007-01-15","l":"092","m":445.91,"y":2007,"z":"A","n":"R"},{"a":"12 VIOLET ST","s":"NARRABRI","p":"2390","t":"Residence","$":190000,"d":"2007-09-05","l":"247","m":796.7,"y":2007,"z":"A","n":"R"},{"a":"12 VIOLET ST","s":"CHATSWOOD","p":"2067","t":"Residence","$":1150000,"d":"2007-07-20","l":"092","m":445.91,"y":2007,"z":"A","n":"R"},{"a":"12 VIOLET ST","s":"NARRABRI","p":"2390","t":"Residence","$":190000,"d":"2007-09-05","l":"247","m":796.7,"y":2007,"z":"A","n":"R"}]}