{"address":"1/316 BONDI RD","count":6,"properties":[{"a":"1/316 BONDI RD","s":"BONDI","p":"2026","t":"Residence","$":3500000,"d":"2006-12-15","l":"209","m":0,"y":2007,"z":"","n":"R"},{"a":"1/316 BONDI RD","s":"BONDI","p":"2026","t":"Residence","$":3500000,"d":"2006-12-15","l":"209","m":0,"y":2007,"z":"","n":"R"},{"a":"1/316 BONDI RD","s":"BONDI","p":"2026","t":"Residence","$":3500000,"d":"2006-12-15","l":"209","m":0,"y":2007,"z":"","n":"R"},{"a":"1/316 BONDI RD","s":"BONDI","p":"2026","t":"Residence","$":3500000,"d":"2006-12-15","l":"209","m":0,"y":2007,"z":"","n":"R"},{"a":"1/316 BONDI RD","s":"BONDI","p":"2026","t":"Residence","$":3500000,"d":"2006-12-15","l":"209","m":0,"y":2007,"z":"","n":"R"},{"a":"1/316 BONDI RD","s":"BONDI","p":"2026","t":"Residence","$":3500000,"d":"2006-12-15","l":"209","m":0,"y":2007,"z":"","n":"R"}]}