{"address":"910 NOBBYS RD","count":4,"properties":[{"a":"910 NOBBYS RD","s":"BARMEDMAN","p":"2668","t":"FARM","$":956902,"d":"2005-05-02","l":"231","m":548.9,"y":2007,"z":"R","n":"3"},{"a":"910 NOBBYS RD","s":"BARMEDMAN","p":"2668","t":"FARM","$":854503,"d":"2005-05-02","l":"231","m":548.9,"y":2007,"z":"R","n":"3"},{"a":"910 NOBBYS RD","s":"BARMEDMAN","p":"2668","t":"FARM","$":956902,"d":"2005-05-02","l":"231","m":548.9,"y":2007,"z":"R","n":"3"},{"a":"910 NOBBYS RD","s":"BARMEDMAN","p":"2668","t":"FARM","$":854503,"d":"2005-05-02","l":"231","m":548.9,"y":2007,"z":"R","n":"3"}]}