{"address":"ELSIE ST","count":6,"properties":[{"a":"ELSIE ST","s":"BANORA POINT","p":"2486","t":"Residence","$":275000,"d":"2007-07-09","l":"171","m":241.8,"y":2007,"z":"A","n":"R"},{"a":"ELSIE ST","s":"BANORA POINT","p":"2486","t":"Residence","$":258000,"d":"2007-06-22","l":"171","m":248.5,"y":2007,"z":"A","n":"R"},{"a":"ELSIE ST","s":"BANORA POINT","p":"2486","t":"Residence","$":259000,"d":"2007-04-18","l":"171","m":233.2,"y":2007,"z":"A","n":"R"},{"a":"ELSIE ST","s":"BANORA POINT","p":"2486","t":"Residence","$":277500,"d":"2007-04-20","l":"171","m":438.3,"y":2007,"z":"A","n":"R"},{"a":"ELSIE ST","s":"BANORA POINT","p":"2486","t":"Residence","$":256000,"d":"2007-06-29","l":"171","m":249.5,"y":2007,"z":"A","n":"R"},{"a":"ELSIE ST","s":"BANORA POINT","p":"2486","t":"Residence","$":289000,"d":"2007-10-17","l":"171","m":361.5,"y":2007,"z":"A","n":"R"}]}