{"address":"HARBOR RD","count":8,"properties":[{"a":"HARBOR RD","s":"MURRAMI","p":"2705","t":"FARM/RURAL","$":95000,"d":"2008-01-11","l":"065","m":22.37,"y":2008,"z":"R","n":"3"},{"a":"HARBOR RD","s":"MURRAMI","p":"2705","t":"FARM","$":640000,"d":"2007-11-20","l":"065","m":22.37,"y":2008,"z":"R","n":"3"},{"a":"HARBOR RD","s":"MURRAMI","p":"2705","t":"FARM/RURAL","$":240000,"d":"2008-01-11","l":"065","m":19.98,"y":2008,"z":"R","n":"3"},{"a":"HARBOR RD","s":"MURRAMI","p":"2705","t":"FARM","$":605129,"d":"2007-11-20","l":"065","m":19.98,"y":2008,"z":"R","n":"3"},{"a":"HARBOR RD","s":"MURRAMI","p":"2705","t":"FARM/RURAL","$":95000,"d":"2008-01-11","l":"065","m":22.37,"y":2008,"z":"R","n":"3"},{"a":"HARBOR RD","s":"MURRAMI","p":"2705","t":"FARM","$":640000,"d":"2007-11-20","l":"065","m":22.37,"y":2008,"z":"R","n":"3"},{"a":"HARBOR RD","s":"MURRAMI","p":"2705","t":"FARM/RURAL","$":240000,"d":"2008-01-11","l":"065","m":19.98,"y":2008,"z":"R","n":"3"},{"a":"HARBOR RD","s":"MURRAMI","p":"2705","t":"FARM","$":605129,"d":"2007-11-20","l":"065","m":19.98,"y":2008,"z":"R","n":"3"}]}