{"address":"22 HIGH ST","count":4,"properties":[{"a":"22 HIGH ST","s":"TORONTO","p":"2283","t":"INDUSTRIAL SH(LOT 4)","$":95000,"d":"2007-12-20","l":"004","m":809.4,"y":2008,"z":"I","n":"3"},{"a":"22 HIGH ST","s":"TORONTO","p":"2283","t":"INDUSTRIAL","$":95000,"d":"2007-12-20","l":"004","m":809.4,"y":2008,"z":"I","n":"3"},{"a":"22 HIGH ST","s":"TORONTO","p":"2283","t":"INDUSTRIAL","$":95000,"d":"2007-12-20","l":"004","m":809.4,"y":2008,"z":"I","n":"3"},{"a":"22 HIGH ST","s":"CESSNOCK","p":"2325","t":"Residence","$":275000,"d":"2008-09-16","l":"001","m":809.43,"y":2008,"z":"A","n":"R"}]}