{"address":"1/258 OLD SOUTH HEAD RD","count":3,"properties":[{"a":"1/258 OLD SOUTH HEAD RD","s":"BELLEVUE HILL","p":"2023","t":"Residence","$":390000,"d":"2008-03-12","l":"210","m":0,"y":2008,"z":"","n":"R"},{"a":"1/258 OLD SOUTH HEAD RD","s":"BELLEVUE HILL","p":"2023","t":"Residence","$":390000,"d":"2008-03-12","l":"210","m":0,"y":2008,"z":"","n":"R"},{"a":"1/258 OLD SOUTH HEAD RD","s":"BELLEVUE HILL","p":"2023","t":"Residence","$":430000,"d":"2008-11-25","l":"210","m":0,"y":2008,"z":"","n":"R"}]}