{"address":"RIALTO PL","count":8,"properties":[{"a":"RIALTO PL","s":"KELLYVILLE","p":"2155","t":"Vacant Land","$":260000,"d":"2001-08-02","l":"081","m":701,"y":2001,"z":"","n":"V"},{"a":"RIALTO PL","s":"KELLYVILLE","p":"2155","t":"Residence","$":265000,"d":"2001-08-13","l":"081","m":776.9,"y":2001,"z":"","n":"R"},{"a":"RIALTO PL","s":"KELLYVILLE","p":"2155","t":"Vacant Land","$":250000,"d":"2001-08-03","l":"081","m":658.8,"y":2001,"z":"","n":"V"},{"a":"RIALTO PL","s":"KELLYVILLE","p":"2155","t":"Residence","$":440800,"d":"2001-11-26","l":"081","m":600,"y":2001,"z":"","n":"R"},{"a":"RIALTO PL","s":"KELLYVILLE","p":"2155","t":"Residence","$":529000,"d":"2001-11-30","l":"081","m":662.9,"y":2001,"z":"","n":"R"},{"a":"RIALTO PL","s":"KELLYVILLE","p":"2155","t":"Vacant Land","$":270000,"d":"2001-11-22","l":"081","m":652.2,"y":2001,"z":"","n":"V"},{"a":"RIALTO PL","s":"KELLYVILLE","p":"2155","t":"Vacant Land","$":175000,"d":"2001-09-20","l":"081","m":754.6,"y":2001,"z":"","n":"V"},{"a":"RIALTO PL","s":"KELLYVILLE","p":"2155","t":"Vacant Land","$":235000,"d":"2001-08-16","l":"081","m":600,"y":2001,"z":"","n":"V"}]}