{"address":"2/228 CONDAMINE ST","count":5,"properties":[{"a":"2/228 CONDAMINE ST","s":"MANLY VALE","p":"2093","t":"Residence","$":370000,"d":"2005-12-21","l":"091","m":0,"y":2006,"z":"","n":"R"},{"a":"2/228 CONDAMINE ST","s":"MANLY VALE","p":"2093","t":"Residence","$":298000,"d":"2006-11-21","l":"091","m":0,"y":2006,"z":"","n":"R"},{"a":"2/228 CONDAMINE ST","s":"MANLY VALE","p":"2093","t":"Residence","$":370000,"d":"2005-12-21","l":"091","m":0,"y":2006,"z":"","n":"R"},{"a":"2/228 CONDAMINE ST","s":"MANLY VALE","p":"2093","t":"Residence","$":370000,"d":"2005-12-21","l":"091","m":0,"y":2006,"z":"","n":"R"},{"a":"2/228 CONDAMINE ST","s":"MANLY VALE","p":"2093","t":"Residence","$":370000,"d":"2005-12-21","l":"091","m":0,"y":2006,"z":"","n":"R"}]}